Lab1/collatz.sv
// CSEE 4840 Lab 1: Run and Display Collatz Conjecture Iteration Counts
//
// Spring 2024
//
// By: Hongkuan Yu, Yelin Mao, Yuqi Lin
// Uni: hy2819, ym3000, yl5334

module collatz( input logic         clk,   // Clock
		input logic 	    go,    // Load value from n; start iterating
		input logic  [31:0] n,     // Start value; only read when go = 1
		output logic [31:0] dout,  // Iteration value: true after go = 1
		output logic 	    done); // True when dout reaches 1

   always_ff @(posedge clk) begin
      if (go) begin
         dout <= n;  
      end 
      else begin
         if (dout == 32'h1) begin
            dout <= dout;
         end
         else if (dout % 32'h2 == 32'h0) begin
            dout <= dout / 32'h2;
         end
         else begin
            dout <= (32'h3 * dout) + 32'h1;
         end
      end
   end

   always_comb begin
      if (dout == 32'h1) begin
            done = 1;
      end
      else begin
            done = 0;
      end
   end 

endmodule

Lab1/range.sv
// CSEE 4840 Lab 1: Run and Display Collatz Conjecture Iteration Counts
//
// Spring 2024
//
// By: Hongkuan Yu, Yelin Mao, Yuqi Lin
// Uni: hy2819, ym3000, yl5334

module range
   #(parameter
     RAM_WORDS = 16,            // Number of counts to store in RAM
     RAM_ADDR_BITS = 4)         // Number of RAM address bits
   (input logic         clk,    // Clock
    input logic 	go,     // Read start and start testing
    input logic [31:0] 	start,  // Number to start from or count to read
    output logic 	done,   // True once memory is filled
    output logic [15:0] count); // Iteration count once finished

   logic 		cgo;    // "go" for the Collatz iterator
   logic                cdone;  // "done" from the Collatz iterator
   logic [31:0] 	n;      // number to start the Collatz iterator

// verilator lint_off PINCONNECTEMPTY
   
   // Instantiate the Collatz iterator
   collatz c1(.clk(clk),
	      .go(cgo),
	      .n(n),
	      .done(cdone),
	      .dout());

   logic [RAM_ADDR_BITS - 1:0] 	 num;         // The RAM address to write
   logic 			 running = 0; // True during the iterations

   /* Replace this comment and the code below with your solution,
      which should generate running, done, cgo, n, num, we, and din */
   always_ff @(posedge clk) begin
      if (go) begin
         running <= 1;
         n <= start;
         num <= {RAM_ADDR_BITS{1'b0}};
         cgo <= 1;
         din <= 16'b1;
      end
      else begin
         if (num != {RAM_ADDR_BITS{1'b1}}) begin
            if (cgo) begin
               running <= 1;
               cgo <= 0;
               din <= 16'b1;               
            end
            else begin
               running <= 1;
               din <= din + 16'b1; 
               if (cdone) begin
                  cgo <= 1;
                  n <= n + 32'h1;
                  num <= num + 1;
                  din <= din;
               end
            end
         end
         else begin
            if (cgo) begin
               running <= 1;
               cgo <= 0;
               din <= 16'b1;               
            end
            else begin
               din <= din + 16'b1;
               running <= 1;
               if (cdone) begin
                  din <= din;                 
                  running <= 0;
                  if (running == 1) begin
                     done <= 1;
                     n <= n + 32'h1;
                  end
                  else begin
                     done <= 0;
                     n <= n;
                  end
               end
            end
         end
      end
   end
   
   always_comb begin
      if (cdone && running) begin
         we = 1;
         if (cgo || done) begin
            we = 0;
         end
      end
      else begin
         we = 0;
      end
   end
   /* Replace this comment and the code above with your solution */

   logic 			 we;                    // Write din to addr
   logic [15:0] 		 din;                   // Data to write
   logic [15:0] 		 mem[RAM_WORDS - 1:0];  // The RAM itself
   logic [RAM_ADDR_BITS - 1:0] 	 addr;                  // Address to read/write

   assign addr = we ? num : start[RAM_ADDR_BITS-1:0];
   
   always_ff @(posedge clk) begin
      if (we) mem[addr] <= din;
      count <= mem[addr];      
   end

endmodule

Lab1/range.vcd
$version Generated by VerilatedVcd $end
$date Fri Feb  9 02:37:18 2024
 $end
$timescale   1ns $end

 $scope module TOP $end
  $var wire  1 /" clk $end
  $var wire 16 O" count [15:0] $end
  $var wire  1 G" done $end
  $var wire  1 7" go $end
  $var wire 32 ?" start [31:0] $end
  $scope module range $end
   $var wire 32 _" RAM_ADDR_BITS [31:0] $end
   $var wire 32 W" RAM_WORDS [31:0] $end
   $var wire  4 3 addr [3:0] $end
   $var wire  1 C cdone $end
   $var wire  1 ; cgo $end
   $var wire  1 /" clk $end
   $var wire 16 O" count [15:0] $end
   $var wire 16 [ din [15:0] $end
   $var wire  1 G" done $end
   $var wire  1 7" go $end
   $var wire 16 c mem(0) [15:0] $end
   $var wire 16 d mem(1) [15:0] $end
   $var wire 16 m mem(10) [15:0] $end
   $var wire 16 n mem(11) [15:0] $end
   $var wire 16 o mem(12) [15:0] $end
   $var wire 16 p mem(13) [15:0] $end
   $var wire 16 q mem(14) [15:0] $end
   $var wire 16 r mem(15) [15:0] $end
   $var wire 16 e mem(2) [15:0] $end
   $var wire 16 f mem(3) [15:0] $end
   $var wire 16 g mem(4) [15:0] $end
   $var wire 16 h mem(5) [15:0] $end
   $var wire 16 i mem(6) [15:0] $end
   $var wire 16 j mem(7) [15:0] $end
   $var wire 16 k mem(8) [15:0] $end
   $var wire 16 l mem(9) [15:0] $end
   $var wire 32 K n [31:0] $end
   $var wire  4 S num [3:0] $end
   $var wire  1 # running $end
   $var wire 32 ?" start [31:0] $end
   $var wire  1 + we $end
   $scope module c1 $end
    $var wire  1 /" clk $end
    $var wire  1 C done $end
    $var wire 32 '" dout [31:0] $end
    $var wire  1 ; go $end
    $var wire 32 K n [31:0] $end
   $upscope $end
  $upscope $end
 $upscope $end
$enddefinitions $end


#0
0#
0+
b0111 3
0;
0C
b00000000000000000000000000000000 K
b0000 S
b0000000000000000 [
b0000000000000000 c
b0000000000000000 d
b0000000000000000 e
b0000000000000000 f
b0000000000000000 g
b0000000000000000 h
b0000000000000000 i
b0000000000000000 j
b0000000000000000 k
b0000000000000000 l
b0000000000000000 m
b0000000000000000 n
b0000000000000000 o
b0000000000000000 p
b0000000000000000 q
b0000000000000000 r
b00000000000000000000000000000000 '"
0/"
17"
b00000000000000000000000000000111 ?"
0G"
b0000000000000000 O"
b00000000000000000000000000010000 W"
b00000000000000000000000000000100 _"
#10
1#
1;
b00000000000000000000000000000111 K
b0000000000000001 [
1/"
#20
0/"
#30
b00000000000000000000000000000111 '"
1/"
#40
0/"
07"
#50
0;
1/"
#60
0/"
#70
b0000000000000010 [
b00000000000000000000000000010110 '"
1/"
#80
0/"
#90
b0000000000000011 [
b00000000000000000000000000001011 '"
1/"
#100
0/"
#110
b0000000000000100 [
b00000000000000000000000000100010 '"
1/"
#120
0/"
#130
b0000000000000101 [
b00000000000000000000000000010001 '"
1/"
#140
0/"
#150
b0000000000000110 [
b00000000000000000000000000110100 '"
1/"
#160
0/"
#170
b0000000000000111 [
b00000000000000000000000000011010 '"
1/"
#180
0/"
#190
b0000000000001000 [
b00000000000000000000000000001101 '"
1/"
#200
0/"
#210
b0000000000001001 [
b00000000000000000000000000101000 '"
1/"
#220
0/"
#230
b0000000000001010 [
b00000000000000000000000000010100 '"
1/"
#240
0/"
#250
b0000000000001011 [
b00000000000000000000000000001010 '"
1/"
#260
0/"
#270
b0000000000001100 [
b00000000000000000000000000000101 '"
1/"
#280
0/"
#290
b0000000000001101 [
b00000000000000000000000000010000 '"
1/"
#300
0/"
#310
b0000000000001110 [
b00000000000000000000000000001000 '"
1/"
#320
0/"
#330
b0000000000001111 [
b00000000000000000000000000000100 '"
1/"
#340
0/"
#350
b0000000000010000 [
b00000000000000000000000000000010 '"
1/"
#360
0/"
#370
1+
b0000 3
1C
b0000000000010001 [
b00000000000000000000000000000001 '"
1/"
#380
0/"
#390
0+
b0111 3
1;
b00000000000000000000000000001000 K
b0001 S
b0000000000010001 c
1/"
#400
0/"
#410
0;
0C
b0000000000000001 [
b00000000000000000000000000001000 '"
1/"
#420
0/"
#430
b0000000000000010 [
b00000000000000000000000000000100 '"
1/"
#440
0/"
#450
b0000000000000011 [
b00000000000000000000000000000010 '"
1/"
#460
0/"
#470
1+
b0001 3
1C
b0000000000000100 [
b00000000000000000000000000000001 '"
1/"
#480
0/"
#490
0+
b0111 3
1;
b00000000000000000000000000001001 K
b0010 S
b0000000000000100 d
1/"
#500
0/"
#510
0;
0C
b0000000000000001 [
b00000000000000000000000000001001 '"
1/"
#520
0/"
#530
b0000000000000010 [
b00000000000000000000000000011100 '"
1/"
#540
0/"
#550
b0000000000000011 [
b00000000000000000000000000001110 '"
1/"
#560
0/"
#570
b0000000000000100 [
b00000000000000000000000000000111 '"
1/"
#580
0/"
#590
b0000000000000101 [
b00000000000000000000000000010110 '"
1/"
#600
0/"
#610
b0000000000000110 [
b00000000000000000000000000001011 '"
1/"
#620
0/"
#630
b0000000000000111 [
b00000000000000000000000000100010 '"
1/"
#640
0/"
#650
b0000000000001000 [
b00000000000000000000000000010001 '"
1/"
#660
0/"
#670
b0000000000001001 [
b00000000000000000000000000110100 '"
1/"
#680
0/"
#690
b0000000000001010 [
b00000000000000000000000000011010 '"
1/"
#700
0/"
#710
b0000000000001011 [
b00000000000000000000000000001101 '"
1/"
#720
0/"
#730
b0000000000001100 [
b00000000000000000000000000101000 '"
1/"
#740
0/"
#750
b0000000000001101 [
b00000000000000000000000000010100 '"
1/"
#760
0/"
#770
b0000000000001110 [
b00000000000000000000000000001010 '"
1/"
#780
0/"
#790
b0000000000001111 [
b00000000000000000000000000000101 '"
1/"
#800
0/"
#810
b0000000000010000 [
b00000000000000000000000000010000 '"
1/"
#820
0/"
#830
b0000000000010001 [
b00000000000000000000000000001000 '"
1/"
#840
0/"
#850
b0000000000010010 [
b00000000000000000000000000000100 '"
1/"
#860
0/"
#870
b0000000000010011 [
b00000000000000000000000000000010 '"
1/"
#880
0/"
#890
1+
b0010 3
1C
b0000000000010100 [
b00000000000000000000000000000001 '"
1/"
#900
0/"
#910
0+
b0111 3
1;
b00000000000000000000000000001010 K
b0011 S
b0000000000010100 e
1/"
#920
0/"
#930
0;
0C
b0000000000000001 [
b00000000000000000000000000001010 '"
1/"
#940
0/"
#950
b0000000000000010 [
b00000000000000000000000000000101 '"
1/"
#960
0/"
#970
b0000000000000011 [
b00000000000000000000000000010000 '"
1/"
#980
0/"
#990
b0000000000000100 [
b00000000000000000000000000001000 '"
1/"
#1000
0/"
#1010
b0000000000000101 [
b00000000000000000000000000000100 '"
1/"
#1020
0/"
#1030
b0000000000000110 [
b00000000000000000000000000000010 '"
1/"
#1040
0/"
#1050
1+
b0011 3
1C
b0000000000000111 [
b00000000000000000000000000000001 '"
1/"
#1060
0/"
#1070
0+
b0111 3
1;
b00000000000000000000000000001011 K
b0100 S
b0000000000000111 f
1/"
#1080
0/"
#1090
0;
0C
b0000000000000001 [
b00000000000000000000000000001011 '"
1/"
#1100
0/"
#1110
b0000000000000010 [
b00000000000000000000000000100010 '"
1/"
#1120
0/"
#1130
b0000000000000011 [
b00000000000000000000000000010001 '"
1/"
#1140
0/"
#1150
b0000000000000100 [
b00000000000000000000000000110100 '"
1/"
#1160
0/"
#1170
b0000000000000101 [
b00000000000000000000000000011010 '"
1/"
#1180
0/"
#1190
b0000000000000110 [
b00000000000000000000000000001101 '"
1/"
#1200
0/"
#1210
b0000000000000111 [
b00000000000000000000000000101000 '"
1/"
#1220
0/"
#1230
b0000000000001000 [
b00000000000000000000000000010100 '"
1/"
#1240
0/"
#1250
b0000000000001001 [
b00000000000000000000000000001010 '"
1/"
#1260
0/"
#1270
b0000000000001010 [
b00000000000000000000000000000101 '"
1/"
#1280
0/"
#1290
b0000000000001011 [
b00000000000000000000000000010000 '"
1/"
#1300
0/"
#1310
b0000000000001100 [
b00000000000000000000000000001000 '"
1/"
#1320
0/"
#1330
b0000000000001101 [
b00000000000000000000000000000100 '"
1/"
#1340
0/"
#1350
b0000000000001110 [
b00000000000000000000000000000010 '"
1/"
#1360
0/"
#1370
1+
b0100 3
1C
b0000000000001111 [
b00000000000000000000000000000001 '"
1/"
#1380
0/"
#1390
0+
b0111 3
1;
b00000000000000000000000000001100 K
b0101 S
b0000000000001111 g
1/"
#1400
0/"
#1410
0;
0C
b0000000000000001 [
b00000000000000000000000000001100 '"
1/"
#1420
0/"
#1430
b0000000000000010 [
b00000000000000000000000000000110 '"
1/"
#1440
0/"
#1450
b0000000000000011 [
b00000000000000000000000000000011 '"
1/"
#1460
0/"
#1470
b0000000000000100 [
b00000000000000000000000000001010 '"
1/"
#1480
0/"
#1490
b0000000000000101 [
b00000000000000000000000000000101 '"
1/"
#1500
0/"
#1510
b0000000000000110 [
b00000000000000000000000000010000 '"
1/"
#1520
0/"
#1530
b0000000000000111 [
b00000000000000000000000000001000 '"
1/"
#1540
0/"
#1550
b0000000000001000 [
b00000000000000000000000000000100 '"
1/"
#1560
0/"
#1570
b0000000000001001 [
b00000000000000000000000000000010 '"
1/"
#1580
0/"
#1590
1+
b0101 3
1C
b0000000000001010 [
b00000000000000000000000000000001 '"
1/"
#1600
0/"
#1610
0+
b0111 3
1;
b00000000000000000000000000001101 K
b0110 S
b0000000000001010 h
1/"
#1620
0/"
#1630
0;
0C
b0000000000000001 [
b00000000000000000000000000001101 '"
1/"
#1640
0/"
#1650
b0000000000000010 [
b00000000000000000000000000101000 '"
1/"
#1660
0/"
#1670
b0000000000000011 [
b00000000000000000000000000010100 '"
1/"
#1680
0/"
#1690
b0000000000000100 [
b00000000000000000000000000001010 '"
1/"
#1700
0/"
#1710
b0000000000000101 [
b00000000000000000000000000000101 '"
1/"
#1720
0/"
#1730
b0000000000000110 [
b00000000000000000000000000010000 '"
1/"
#1740
0/"
#1750
b0000000000000111 [
b00000000000000000000000000001000 '"
1/"
#1760
0/"
#1770
b0000000000001000 [
b00000000000000000000000000000100 '"
1/"
#1780
0/"
#1790
b0000000000001001 [
b00000000000000000000000000000010 '"
1/"
#1800
0/"
#1810
1+
b0110 3
1C
b0000000000001010 [
b00000000000000000000000000000001 '"
1/"
#1820
0/"
#1830
0+
b0111 3
1;
b00000000000000000000000000001110 K
b0111 S
b0000000000001010 i
1/"
#1840
0/"
#1850
0;
0C
b0000000000000001 [
b00000000000000000000000000001110 '"
1/"
#1860
0/"
#1870
b0000000000000010 [
b00000000000000000000000000000111 '"
1/"
#1880
0/"
#1890
b0000000000000011 [
b00000000000000000000000000010110 '"
1/"
#1900
0/"
#1910
b0000000000000100 [
b00000000000000000000000000001011 '"
1/"
#1920
0/"
#1930
b0000000000000101 [
b00000000000000000000000000100010 '"
1/"
#1940
0/"
#1950
b0000000000000110 [
b00000000000000000000000000010001 '"
1/"
#1960
0/"
#1970
b0000000000000111 [
b00000000000000000000000000110100 '"
1/"
#1980
0/"
#1990
b0000000000001000 [
b00000000000000000000000000011010 '"
1/"
#2000
0/"
#2010
b0000000000001001 [
b00000000000000000000000000001101 '"
1/"
#2020
0/"
#2030
b0000000000001010 [
b00000000000000000000000000101000 '"
1/"
#2040
0/"
#2050
b0000000000001011 [
b00000000000000000000000000010100 '"
1/"
#2060
0/"
#2070
b0000000000001100 [
b00000000000000000000000000001010 '"
1/"
#2080
0/"
#2090
b0000000000001101 [
b00000000000000000000000000000101 '"
1/"
#2100
0/"
#2110
b0000000000001110 [
b00000000000000000000000000010000 '"
1/"
#2120
0/"
#2130
b0000000000001111 [
b00000000000000000000000000001000 '"
1/"
#2140
0/"
#2150
b0000000000010000 [
b00000000000000000000000000000100 '"
1/"
#2160
0/"
#2170
b0000000000010001 [
b00000000000000000000000000000010 '"
1/"
#2180
0/"
#2190
1+
1C
b0000000000010010 [
b00000000000000000000000000000001 '"
1/"
#2200
0/"
#2210
0+
1;
b00000000000000000000000000001111 K
b1000 S
b0000000000010010 j
1/"
#2220
0/"
#2230
0;
0C
b0000000000000001 [
b00000000000000000000000000001111 '"
1/"
b0000000000010010 O"
#2240
0/"
#2250
b0000000000000010 [
b00000000000000000000000000101110 '"
1/"
#2260
0/"
#2270
b0000000000000011 [
b00000000000000000000000000010111 '"
1/"
#2280
0/"
#2290
b0000000000000100 [
b00000000000000000000000001000110 '"
1/"
#2300
0/"
#2310
b0000000000000101 [
b00000000000000000000000000100011 '"
1/"
#2320
0/"
#2330
b0000000000000110 [
b00000000000000000000000001101010 '"
1/"
#2340
0/"
#2350
b0000000000000111 [
b00000000000000000000000000110101 '"
1/"
#2360
0/"
#2370
b0000000000001000 [
b00000000000000000000000010100000 '"
1/"
#2380
0/"
#2390
b0000000000001001 [
b00000000000000000000000001010000 '"
1/"
#2400
0/"
#2410
b0000000000001010 [
b00000000000000000000000000101000 '"
1/"
#2420
0/"
#2430
b0000000000001011 [
b00000000000000000000000000010100 '"
1/"
#2440
0/"
#2450
b0000000000001100 [
b00000000000000000000000000001010 '"
1/"
#2460
0/"
#2470
b0000000000001101 [
b00000000000000000000000000000101 '"
1/"
#2480
0/"
#2490
b0000000000001110 [
b00000000000000000000000000010000 '"
1/"
#2500
0/"
#2510
b0000000000001111 [
b00000000000000000000000000001000 '"
1/"
#2520
0/"
#2530
b0000000000010000 [
b00000000000000000000000000000100 '"
1/"
#2540
0/"
#2550
b0000000000010001 [
b00000000000000000000000000000010 '"
1/"
#2560
0/"
#2570
1+
b1000 3
1C
b0000000000010010 [
b00000000000000000000000000000001 '"
1/"
#2580
0/"
#2590
0+
b0111 3
1;
b00000000000000000000000000010000 K
b1001 S
b0000000000010010 k
1/"
b0000000000000000 O"
#2600
0/"
#2610
0;
0C
b0000000000000001 [
b00000000000000000000000000010000 '"
1/"
b0000000000010010 O"
#2620
0/"
#2630
b0000000000000010 [
b00000000000000000000000000001000 '"
1/"
#2640
0/"
#2650
b0000000000000011 [
b00000000000000000000000000000100 '"
1/"
#2660
0/"
#2670
b0000000000000100 [
b00000000000000000000000000000010 '"
1/"
#2680
0/"
#2690
1+
b1001 3
1C
b0000000000000101 [
b00000000000000000000000000000001 '"
1/"
#2700
0/"
#2710
0+
b0111 3
1;
b00000000000000000000000000010001 K
b1010 S
b0000000000000101 l
1/"
b0000000000000000 O"
#2720
0/"
#2730
0;
0C
b0000000000000001 [
b00000000000000000000000000010001 '"
1/"
b0000000000010010 O"
#2740
0/"
#2750
b0000000000000010 [
b00000000000000000000000000110100 '"
1/"
#2760
0/"
#2770
b0000000000000011 [
b00000000000000000000000000011010 '"
1/"
#2780
0/"
#2790
b0000000000000100 [
b00000000000000000000000000001101 '"
1/"
#2800
0/"
#2810
b0000000000000101 [
b00000000000000000000000000101000 '"
1/"
#2820
0/"
#2830
b0000000000000110 [
b00000000000000000000000000010100 '"
1/"
#2840
0/"
#2850
b0000000000000111 [
b00000000000000000000000000001010 '"
1/"
#2860
0/"
#2870
b0000000000001000 [
b00000000000000000000000000000101 '"
1/"
#2880
0/"
#2890
b0000000000001001 [
b00000000000000000000000000010000 '"
1/"
#2900
0/"
#2910
b0000000000001010 [
b00000000000000000000000000001000 '"
1/"
#2920
0/"
#2930
b0000000000001011 [
b00000000000000000000000000000100 '"
1/"
#2940
0/"
#2950
b0000000000001100 [
b00000000000000000000000000000010 '"
1/"
#2960
0/"
#2970
1+
b1010 3
1C
b0000000000001101 [
b00000000000000000000000000000001 '"
1/"
#2980
0/"
#2990
0+
b0111 3
1;
b00000000000000000000000000010010 K
b1011 S
b0000000000001101 m
1/"
b0000000000000000 O"
#3000
0/"
#3010
0;
0C
b0000000000000001 [
b00000000000000000000000000010010 '"
1/"
b0000000000010010 O"
#3020
0/"
#3030
b0000000000000010 [
b00000000000000000000000000001001 '"
1/"
#3040
0/"
#3050
b0000000000000011 [
b00000000000000000000000000011100 '"
1/"
#3060
0/"
#3070
b0000000000000100 [
b00000000000000000000000000001110 '"
1/"
#3080
0/"
#3090
b0000000000000101 [
b00000000000000000000000000000111 '"
1/"
#3100
0/"
#3110
b0000000000000110 [
b00000000000000000000000000010110 '"
1/"
#3120
0/"
#3130
b0000000000000111 [
b00000000000000000000000000001011 '"
1/"
#3140
0/"
#3150
b0000000000001000 [
b00000000000000000000000000100010 '"
1/"
#3160
0/"
#3170
b0000000000001001 [
b00000000000000000000000000010001 '"
1/"
#3180
0/"
#3190
b0000000000001010 [
b00000000000000000000000000110100 '"
1/"
#3200
0/"
#3210
b0000000000001011 [
b00000000000000000000000000011010 '"
1/"
#3220
0/"
#3230
b0000000000001100 [
b00000000000000000000000000001101 '"
1/"
#3240
0/"
#3250
b0000000000001101 [
b00000000000000000000000000101000 '"
1/"
#3260
0/"
#3270
b0000000000001110 [
b00000000000000000000000000010100 '"
1/"
#3280
0/"
#3290
b0000000000001111 [
b00000000000000000000000000001010 '"
1/"
#3300
0/"
#3310
b0000000000010000 [
b00000000000000000000000000000101 '"
1/"
#3320
0/"
#3330
b0000000000010001 [
b00000000000000000000000000010000 '"
1/"
#3340
0/"
#3350
b0000000000010010 [
b00000000000000000000000000001000 '"
1/"
#3360
0/"
#3370
b0000000000010011 [
b00000000000000000000000000000100 '"
1/"
#3380
0/"
#3390
b0000000000010100 [
b00000000000000000000000000000010 '"
1/"
#3400
0/"
#3410
1+
b1011 3
1C
b0000000000010101 [
b00000000000000000000000000000001 '"
1/"
#3420
0/"
#3430
0+
b0111 3
1;
b00000000000000000000000000010011 K
b1100 S
b0000000000010101 n
1/"
b0000000000000000 O"
#3440
0/"
#3450
0;
0C
b0000000000000001 [
b00000000000000000000000000010011 '"
1/"
b0000000000010010 O"
#3460
0/"
#3470
b0000000000000010 [
b00000000000000000000000000111010 '"
1/"
#3480
0/"
#3490
b0000000000000011 [
b00000000000000000000000000011101 '"
1/"
#3500
0/"
#3510
b0000000000000100 [
b00000000000000000000000001011000 '"
1/"
#3520
0/"
#3530
b0000000000000101 [
b00000000000000000000000000101100 '"
1/"
#3540
0/"
#3550
b0000000000000110 [
b00000000000000000000000000010110 '"
1/"
#3560
0/"
#3570
b0000000000000111 [
b00000000000000000000000000001011 '"
1/"
#3580
0/"
#3590
b0000000000001000 [
b00000000000000000000000000100010 '"
1/"
#3600
0/"
#3610
b0000000000001001 [
b00000000000000000000000000010001 '"
1/"
#3620
0/"
#3630
b0000000000001010 [
b00000000000000000000000000110100 '"
1/"
#3640
0/"
#3650
b0000000000001011 [
b00000000000000000000000000011010 '"
1/"
#3660
0/"
#3670
b0000000000001100 [
b00000000000000000000000000001101 '"
1/"
#3680
0/"
#3690
b0000000000001101 [
b00000000000000000000000000101000 '"
1/"
#3700
0/"
#3710
b0000000000001110 [
b00000000000000000000000000010100 '"
1/"
#3720
0/"
#3730
b0000000000001111 [
b00000000000000000000000000001010 '"
1/"
#3740
0/"
#3750
b0000000000010000 [
b00000000000000000000000000000101 '"
1/"
#3760
0/"
#3770
b0000000000010001 [
b00000000000000000000000000010000 '"
1/"
#3780
0/"
#3790
b0000000000010010 [
b00000000000000000000000000001000 '"
1/"
#3800
0/"
#3810
b0000000000010011 [
b00000000000000000000000000000100 '"
1/"
#3820
0/"
#3830
b0000000000010100 [
b00000000000000000000000000000010 '"
1/"
#3840
0/"
#3850
1+
b1100 3
1C
b0000000000010101 [
b00000000000000000000000000000001 '"
1/"
#3860
0/"
#3870
0+
b0111 3
1;
b00000000000000000000000000010100 K
b1101 S
b0000000000010101 o
1/"
b0000000000000000 O"
#3880
0/"
#3890
0;
0C
b0000000000000001 [
b00000000000000000000000000010100 '"
1/"
b0000000000010010 O"
#3900
0/"
#3910
b0000000000000010 [
b00000000000000000000000000001010 '"
1/"
#3920
0/"
#3930
b0000000000000011 [
b00000000000000000000000000000101 '"
1/"
#3940
0/"
#3950
b0000000000000100 [
b00000000000000000000000000010000 '"
1/"
#3960
0/"
#3970
b0000000000000101 [
b00000000000000000000000000001000 '"
1/"
#3980
0/"
#3990
b0000000000000110 [
b00000000000000000000000000000100 '"
1/"
#4000
0/"
#4010
b0000000000000111 [
b00000000000000000000000000000010 '"
1/"
#4020
0/"
#4030
1+
b1101 3
1C
b0000000000001000 [
b00000000000000000000000000000001 '"
1/"
#4040
0/"
#4050
0+
b0111 3
1;
b00000000000000000000000000010101 K
b1110 S
b0000000000001000 p
1/"
b0000000000000000 O"
#4060
0/"
#4070
0;
0C
b0000000000000001 [
b00000000000000000000000000010101 '"
1/"
b0000000000010010 O"
#4080
0/"
#4090
b0000000000000010 [
b00000000000000000000000001000000 '"
1/"
#4100
0/"
#4110
b0000000000000011 [
b00000000000000000000000000100000 '"
1/"
#4120
0/"
#4130
b0000000000000100 [
b00000000000000000000000000010000 '"
1/"
#4140
0/"
#4150
b0000000000000101 [
b00000000000000000000000000001000 '"
1/"
#4160
0/"
#4170
b0000000000000110 [
b00000000000000000000000000000100 '"
1/"
#4180
0/"
#4190
b0000000000000111 [
b00000000000000000000000000000010 '"
1/"
#4200
0/"
#4210
1+
b1110 3
1C
b0000000000001000 [
b00000000000000000000000000000001 '"
1/"
#4220
0/"
#4230
0+
b0111 3
1;
b00000000000000000000000000010110 K
b1111 S
b0000000000001000 q
1/"
b0000000000000000 O"
#4240
0/"
#4250
0;
0C
b0000000000000001 [
b00000000000000000000000000010110 '"
1/"
b0000000000010010 O"
#4260
0/"
#4270
b0000000000000010 [
b00000000000000000000000000001011 '"
1/"
#4280
0/"
#4290
b0000000000000011 [
b00000000000000000000000000100010 '"
1/"
#4300
0/"
#4310
b0000000000000100 [
b00000000000000000000000000010001 '"
1/"
#4320
0/"
#4330
b0000000000000101 [
b00000000000000000000000000110100 '"
1/"
#4340
0/"
#4350
b0000000000000110 [
b00000000000000000000000000011010 '"
1/"
#4360
0/"
#4370
b0000000000000111 [
b00000000000000000000000000001101 '"
1/"
#4380
0/"
#4390
b0000000000001000 [
b00000000000000000000000000101000 '"
1/"
#4400
0/"
#4410
b0000000000001001 [
b00000000000000000000000000010100 '"
1/"
#4420
0/"
#4430
b0000000000001010 [
b00000000000000000000000000001010 '"
1/"
#4440
0/"
#4450
b0000000000001011 [
b00000000000000000000000000000101 '"
1/"
#4460
0/"
#4470
b0000000000001100 [
b00000000000000000000000000010000 '"
1/"
#4480
0/"
#4490
b0000000000001101 [
b00000000000000000000000000001000 '"
1/"
#4500
0/"
#4510
b0000000000001110 [
b00000000000000000000000000000100 '"
1/"
#4520
0/"
#4530
b0000000000001111 [
b00000000000000000000000000000010 '"
1/"
#4540
0/"
#4550
1+
b1111 3
1C
b0000000000010000 [
b00000000000000000000000000000001 '"
1/"
#4560
0/"
#4570
0#
0+
b0111 3
b00000000000000000000000000010111 K
b0000000000010000 r
1/"
1G"
b0000000000000000 O"
#4580
b0000 3
0/"
b00000000000000000000000000000000 ?"
#4590
1/"
0G"
b0000000000010001 O"
#4600
b0001 3
0/"
b00000000000000000000000000000001 ?"
#4610
1/"
b0000000000000100 O"
#4620
b0010 3
0/"
b00000000000000000000000000000010 ?"
#4630
1/"
b0000000000010100 O"
#4640
b0011 3
0/"
b00000000000000000000000000000011 ?"
#4650
1/"
b0000000000000111 O"
#4660
b0100 3
0/"
b00000000000000000000000000000100 ?"
#4670
1/"
b0000000000001111 O"
#4680
b0101 3
0/"
b00000000000000000000000000000101 ?"
#4690
1/"
b0000000000001010 O"
#4700
b0110 3
0/"
b00000000000000000000000000000110 ?"
#4710
1/"
#4720
b0111 3
0/"
b00000000000000000000000000000111 ?"
#4730
1/"
b0000000000010010 O"
#4740
b1000 3
0/"
b00000000000000000000000000001000 ?"
#4750
1/"
#4760
b1001 3
0/"
b00000000000000000000000000001001 ?"
#4770
1/"
b0000000000000101 O"
#4780
b1010 3
0/"
b00000000000000000000000000001010 ?"
#4790
1/"
b0000000000001101 O"
#4800
b1011 3
0/"
b00000000000000000000000000001011 ?"
#4810
1/"
b0000000000010101 O"
#4820
b1100 3
0/"
b00000000000000000000000000001100 ?"
#4830
1/"
#4840
b1101 3
0/"
b00000000000000000000000000001101 ?"
#4850
1/"
b0000000000001000 O"
#4860
b1110 3
0/"
b00000000000000000000000000001110 ?"
#4870
1/"
#4880
b1111 3
0/"
b00000000000000000000000000001111 ?"
#4890
1/"
b0000000000010000 O"
